yamlparams/__init__.py
yamlparams/utils.py
yamlparams-0.0.2.dist-info/LICENSE
yamlparams-0.0.2.dist-info/METADATA
yamlparams-0.0.2.dist-info/WHEEL
yamlparams-0.0.2.dist-info/top_level.txt
yamlparams-0.0.2.dist-info/RECORD
