Metadata-Version: 2.1
Name: yamlparams
Version: 0.0.2
Summary: Config helper
Home-page: https://github.com/Aroize
Author: Ilia Ilmenskii
Author-email: gipermonk@bk.ru
License: UNKNOWN
Platform: UNKNOWN
Classifier: Programming Language :: Python :: 3
Classifier: License :: OSI Approved :: MIT License
Classifier: Operating System :: OS Independent
Requires-Python: >=3.6
